Mohit_SpeechToTextConverter/__init__.py
Mohit_SpeechToTextConverter-0.1.dist-info/METADATA
Mohit_SpeechToTextConverter-0.1.dist-info/WHEEL
Mohit_SpeechToTextConverter-0.1.dist-info/top_level.txt
Mohit_SpeechToTextConverter-0.1.dist-info/RECORD
